src/12306-search-mcp/__init__.py
src/12306-search-mcp/server.py
src/12306-search-mcp/test.py
12306_search_mcp-0.1.4.dist-info/METADATA
12306_search_mcp-0.1.4.dist-info/WHEEL
12306_search_mcp-0.1.4.dist-info/entry_points.txt
12306_search_mcp-0.1.4.dist-info/RECORD
